crate/client/__init__.py
crate/client/_pep440.py
crate/client/blob.py
crate/client/connection.py
crate/client/converter.py
crate/client/cursor.py
crate/client/exceptions.py
crate/client/http.py
crate/testing/__init__.py
crate/testing/layer.py
crate/testing/util.py
crate-2.0.0.dist-info/LICENSE
crate-2.0.0.dist-info/METADATA
crate-2.0.0.dist-info/NOTICE
crate-2.0.0.dist-info/WHEEL
crate-2.0.0.dist-info/top_level.txt
crate-2.0.0.dist-info/RECORD
