Metadata-Version: 2.2
Name: crate
Version: 2.0.0
Summary: CrateDB Python Client
Home-page: https://github.com/crate/crate-python
Author: Crate.io
Author-email: office@crate.io
License: Apache License 2.0
Keywords: cratedb db api dbapi database sql http rdbms olap
Platform: any
Classifier: Development Status :: 5 - Production/Stable
Classifier: Intended Audience :: Developers
Classifier: License :: OSI Approved :: Apache Software License
Classifier: Operating System :: OS Independent
Classifier: Programming Language :: Python
Classifier: Programming Language :: Python :: 3
Classifier: Programming Language :: Python :: 3.6
Classifier: Programming Language :: Python :: 3.7
Classifier: Programming Language :: Python :: 3.8
Classifier: Programming Language :: Python :: 3.9
Classifier: Programming Language :: Python :: 3.10
Classifier: Programming Language :: Python :: 3.11
Classifier: Programming Language :: Python :: 3.12
Classifier: Programming Language :: Python :: 3.13
Classifier: Programming Language :: Python :: Implementation :: CPython
Classifier: Programming Language :: Python :: Implementation :: PyPy
Classifier: Topic :: Database
Requires-Python: >=3.6
License-File: LICENSE
License-File: NOTICE
Requires-Dist: orjson<4
Requires-Dist: urllib3
Requires-Dist: verlib2
Provides-Extra: doc
Requires-Dist: crate-docs-theme>=0.26.5; extra == "doc"
Requires-Dist: sphinx<9,>=3.5; extra == "doc"
Provides-Extra: test
Requires-Dist: backports.zoneinfo<1; python_version < "3.9" and extra == "test"
Requires-Dist: certifi; extra == "test"
Requires-Dist: createcoverage<2,>=1; extra == "test"
Requires-Dist: mypy<1.15; extra == "test"
Requires-Dist: poethepoet<0.33; extra == "test"
Requires-Dist: ruff<0.10; extra == "test"
Requires-Dist: stopit<2,>=1.1.2; extra == "test"
Requires-Dist: pytz; extra == "test"
Requires-Dist: zc.customdoctests<2,>=1.0.1; extra == "test"
Requires-Dist: zope.testing<6,>=4; extra == "test"
Requires-Dist: zope.testrunner<7,>=5; extra == "test"
Dynamic: author
Dynamic: author-email
Dynamic: classifier
Dynamic: description
Dynamic: description-content-type
Dynamic: home-page
Dynamic: keywords
Dynamic: license
Dynamic: platform
Dynamic: provides-extra
Dynamic: requires-dist
Dynamic: requires-python
Dynamic: summary
